lambapi/__init__.py
lambapi/base_router.py
lambapi/cli.py
lambapi/core.py
lambapi/cors.py
lambapi/dependencies.py
lambapi/dependency_resolver.py
lambapi/dev_tools.py
lambapi/error_handlers.py
lambapi/exceptions.py
lambapi/json_handler.py
lambapi/request.py
lambapi/response.py
lambapi/router.py
lambapi/template_loader.py
lambapi/utils.py
lambapi/uvicorn_server.py
lambapi/validation.py
lambapi/auth/__init__.py
lambapi/auth/dynamodb_auth.py
lambapi/templates/basic_app.py
lambapi/templates/crud_app.py
lambapi-0.2.17.dist-info/licenses/LICENSE
lambapi-0.2.17.dist-info/METADATA
lambapi-0.2.17.dist-info/WHEEL
lambapi-0.2.17.dist-info/entry_points.txt
lambapi-0.2.17.dist-info/top_level.txt
lambapi-0.2.17.dist-info/RECORD
