Metadata-Version: 2.4
Name: lambapi
Version: 0.2.17
Summary: モダンな AWS Lambda 用 API フレームワーク
Home-page: https://github.com/sskyh0208/lambapi
Author: Yoshihiro Sasaki
Author-email: Yoshihiro Sasaki <sskyh1988@gmail.com>
License: MIT
Project-URL: Homepage, https://github.com/sskyh0208/lambapi
Project-URL: Documentation, https://sskyh0208.github.io/lambapi/
Project-URL: Repository, https://github.com/sskyh0208/lambapi
Project-URL: Bug Tracker, https://github.com/sskyh0208/lambapi/issues
Keywords: lambda,api,aws,serverless,http,rest
Classifier: Development Status :: 3 - Alpha
Classifier: Intended Audience :: Developers
Classifier: License :: OSI Approved :: MIT License
Classifier: Operating System :: OS Independent
Classifier: Programming Language :: Python :: 3
Classifier: Programming Language :: Python :: 3.10
Classifier: Programming Language :: Python :: 3.11
Classifier: Programming Language :: Python :: 3.12
Classifier: Programming Language :: Python :: 3.13
Classifier: Topic :: Internet :: WWW/HTTP :: HTTP Servers
Classifier: Topic :: Software Development :: Libraries :: Python Modules
Requires-Python: >=3.10
License-File: LICENSE
Provides-Extra: dev
Requires-Dist: pytest>=6.0; extra == "dev"
Requires-Dist: pytest-cov>=2.0; extra == "dev"
Requires-Dist: black>=22.0; extra == "dev"
Requires-Dist: flake8>=4.0; extra == "dev"
Requires-Dist: mypy>=0.900; extra == "dev"
Requires-Dist: isort>=5.0; extra == "dev"
Requires-Dist: bandit[toml]>=1.7; extra == "dev"
Requires-Dist: safety>=2.0; extra == "dev"
Requires-Dist: watchdog>=3.0; extra == "dev"
Requires-Dist: pre-commit>=3.0; extra == "dev"
Requires-Dist: uvicorn[standard]>=0.24.0; extra == "dev"
Requires-Dist: pynamodb>=5.0; extra == "dev"
Requires-Dist: moto[dynamodb]>=4.0; extra == "dev"
Provides-Extra: validation
Requires-Dist: pydantic>=2.0; extra == "validation"
Provides-Extra: auth
Requires-Dist: boto3>=1.28.0; extra == "auth"
Requires-Dist: PyJWT>=2.8.0; extra == "auth"
Requires-Dist: bcrypt>=4.0.0; extra == "auth"
Requires-Dist: cryptography>=41.0.0; extra == "auth"
Requires-Dist: pynamodb>=5.0; extra == "auth"
Requires-Dist: moto[dynamodb]>=4.0; extra == "auth"
Dynamic: author
Dynamic: home-page
Dynamic: license-file
Dynamic: requires-python
